<?xml version="1.0" encoding="utf-8"?>
<!DOCTYPE Summary >
<Summary id="CDR0000747947" LegacyPDQID=""><SummaryMetaData><SummaryType>Prevention</SummaryType><SummaryAudience>Health professionals</SummaryAudience><SummaryLanguage>Spanish</SummaryLanguage><SummaryDescription>Sumario de información revisada por expertos sobre los factores que pueden influir en el riesgo de cáncer de próstata y sobre la investigación dirigida a la prevención de esta enfermedad. </SummaryDescription><SummaryURL xref="http://cancer.gov/espanol/tipos/prostata/pro/prevencion-prostata-pdq">Cáncer de próstata (PDQ®): Prevención</SummaryURL><MainTopics><TermRef ref="CDR0000038782">prostate cancer</TermRef></MainTopics></SummaryMetaData><SummaryTitle>Prevención del cáncer de próstata (PDQ®)</SummaryTitle><AltTitle TitleType="Short">Prevención del cáncer de próstata</AltTitle><SummarySection id="_1"><Title>Descripción</Title><Para id="_2">Nota: también están disponibles sumarios del PDQ por separado sobre  <SummaryRef href="CDR0000747922" url="/espanol/tipos/prostata/pro/deteccion-prostata-pdq">Exámenes de detección del cáncer de próstata</SummaryRef>,  <SummaryRef href="CDR0000256716" url="/espanol/tipos/prostata/pro/tratamiento-prostata-pdq">Tratamiento del cáncer de próstata</SummaryRef> y <SummaryRef href="CDR0000733829" url="/espanol/publicaciones/pdq/grados-comprobacion/deteccion-prevencion">Grados de comprobación científica de los estudios de investigación sobre detección y prevención del cáncer</SummaryRef>.</Para><SummarySection id="_3"><Title>Beneficios de la quimioprevención con finasterida y dutasterida</Title><Para id="_4">Sobre la base de datos probatorios sólidos, la quimioprevención con finasterida y dutasterida reduce la incidencia del cáncer de próstata, pero estos resultan inadecuados para determinar si la quimioprevención con finasterida o dutasterida reduce la mortalidad por cáncer de próstata.</Para><Para id="_5"><Strong>Magnitud del efecto: la reducción absoluta de la incidencia  con finasterida por más de 7 años fue de 6% (24,4% con placebo y 18,4% con  finasterida); la reducción relativa del riesgo (RRR) por incidencia fue de  24,8% (intervalo de confianza [IC] 95%, 18,6–30,6%). No hubo diferencia en cuanto al número de hombres que murieron por cáncer de próstata en ambos grupos, aunque el número de muertes fue pequeño.</Strong></Para><Para id="_6"><Strong>En el ensayo con dutasterida, con el uso de la tasa bruta de restricción, la reducción absoluta del riesgo fue de 5,1% a 4 años y la RRR fue de 22,8% (IC  95%, 15,2–29,8%, <Emphasis>P</Emphasis> &lt; 0,001). No hubo diferencia en cuanto al cáncer de próstata o la mortalidad general, aunque el número de muertes fue pequeño y ninguna se debió al cáncer de próstata. La reducción en la incidencia de cáncer de próstata se presentó principalmente en los cánceres con puntaje de Gleason  5 a 6.<Reference refidx="1"/> La reducción de la incidencia principalmente en los cánceres de crecimiento más lento (es decir, Gleason  5–6) y no en los cánceres de crecimiento más rápido  (es decir, Gleason  7–10), plantea el interrogante de si esta reducción de la incidencia conllevará alguna reducción de la mortalidad. Por el momento, esta pregunta se encuentra sin respuesta.</Strong></Para><ItemizedList id="_7" Style="simple">
     <ListItem>Diseño del estudio: dos ensayos controlados aleatorizados, uno con finasterida y el otro con dutasterida.</ListItem><ListItem>Validez interna: buena, en cuanto a la incidencia y precaria, en cuanto a la mortalidad.</ListItem><ListItem>Congruencia: buena.</ListItem><ListItem>Validez externa: los estudios se enfocaron en poblaciones diferentes. El ensayo con finasterida inscribió a hombres con antígeno prostático específico (APE) mayor de 3 ng/ml, lo que constituye la mayoría de los hombres estadounidenses, pero hombres con un riesgo menor de cáncer. En el ensayo con dutasterida, los hombres presentaron un riesgo un poco más alto con un APE de 2,5 a 10,0 y una biopsia previa negativa. Como tal, los resultados son generalizables, principalmente, en estas poblaciones respectivas.</ListItem></ItemizedList></SummarySection><SummarySection id="_8"><Title>Perjuicios provocados por la quimioprevención con finasterida y dutasterida</Title><SummarySection id="_9"><Title>Finasterida</Title><Para id="_10">Los hombres en el grupo de finasterida presentaron, de manera estadísticamente significativa, una mayor disfunción eréctil, pérdida de la libido y ginecomastias que los hombres en el grupo de placebo.  Durante el estudio, los hombres del grupo de finasterida presentaron una incidencia estadísticamente significativa de cánceres de grado alto  (suma de Gleason  8–10).<Reference refidx="2"/> Sea que esto fuese un artefacto histológico o no, resultad incierto.</Para><Para id="_11"><Strong>Magnitud del efecto: se observaron aumentos estadísticamente significativos en los siguientes resultados del grupo de finasterida (una fracción mayor de hombres del grupo de finasterida [36,8%] descontinuó el tratamiento de forma temporal en algún momento durante el estudio por razones no relacionadas con  la muerte o el diagnóstico de cáncer de próstata, que en el grupo de placebo [28,9%]):</Strong></Para><ItemizedList id="_12" Style="simple">
     <ListItem>Porcentaje del grupo de finasterida comparado con el porcentaje del grupo de placebo:<ItemizedList id="_13" Style="simple">
     <ListItem>Volumen de eyaculación reducido (60,4 vs. 47,3%).</ListItem><ListItem>     Disfunción eréctil (67,4 vs. 61,5%).</ListItem><ListItem>     Pérdida de la libido (65,4 vs. 59,6%).</ListItem><ListItem>     Ginecomastia (4,5 vs. 2,8%).</ListItem></ItemizedList></ListItem></ItemizedList></SummarySection><SummarySection id="_14"><Title>Dutasterida</Title><Para id="_16">En general, 4,3% de los hombres en el grupo de dutasterida, en comparación con  2% de los hombres en el grupo de placebo abandonaron el ensayo debido a los efectos adversos del medicamento (<Emphasis>P</Emphasis> &lt; 0,001). Los hombres del grupo de dutasterida presentaron una mayor incidencia de disminución de la libido, pérdida de la libido, disminución del volumen de semen, disfunción eréctil y ginecomastia, que los hombres del grupo de placebo.<Reference refidx="1"/></Para><Para id="_17"><Strong>Magnitud del efecto: se observaron aumentos estadísticamente significativos en los siguientes resultados del grupo de dutasterida:</Strong></Para><ItemizedList id="_18" Style="simple">
     <ListItem>Porcentaje del grupo de dutasterida comparado con el porcentaje del grupo de placebo:<ItemizedList id="_19" Style="simple">
     <ListItem>Disminución de la libido (3,3 vs. 1,6%).</ListItem><ListItem>     Pérdida de la libido (1,9 vs. 1,3%).</ListItem><ListItem>Disminución del volumen de semen (1,4 vs. 0,2%)</ListItem><ListItem>     Disfunción eréctil (9,0 vs. 5,7%).</ListItem><ListItem>     Ginecomastia (1,9 vs. 1,0%).</ListItem></ItemizedList></ListItem></ItemizedList><ItemizedList id="_20" Style="simple">
     <ListItem>Diseño del estudio: dos ensayos controlados aleatorizados, uno con finasterida y el otro con dutasterida.</ListItem><ListItem>Validez interna: buena. El ensayo con finasterida usó dos evaluaciones de la función sexual realizadas por los mismos sujetos, que se llevaron a cabo  en el momento de inscripción, aleatorización, a los 6 meses y, luego, anualmente en el transcurso de 7 años de estudio. El ensayo con dutasterida usó una evaluación de la función sexual tras completar el período de preinclusión con placebo, y de ahí en adelante esta se repitió anualmente.</ListItem><ListItem>Congruencia: buena (otros datos probatorios diferentes a los ensayos controlados aleatorizados sustentan estos efectos). </ListItem><ListItem>Validez externa: como se indicó anteriormente, los estudios evaluaron dos poblaciones diferentes: un APE menor o igual a 3 ng/ml en  el ensayo con finasterida, y un APE de 2,5 a 10,0 ng/ml con una biopsia previa negativa en el ensayo REDUCE. Los resultados son más generalizables a estas dos poblaciones.</ListItem></ItemizedList></SummarySection></SummarySection><SummarySection id="_21"><Title>Otras intervenciones de prevención</Title><Para id="_22">El <ProtocolRef href="CDR0000068277" nct_id="NCT00006392">Selenium and Vitamin E Cancer Prevention Trial (SELECT [NCT00006392])</ProtocolRef>, ensayo numeroso, aleatorizado, controlado con placebo, de vitamina E y selenio, no mostró reducción  de cáncer de próstata durante el período de prevalencia, pero sí un aumento del riesgo de cáncer de próstata con la vitamina E sola.<Reference refidx="3"/></Para><Para id="_23"><Strong>Magnitud del efecto: en comparación con el grupo de placebo, en el cual 529 hombres presentaron cáncer de próstata, hubo un aumento estadísticamente significativo en el grupo de vitamina E (620 casos), pero no en el grupo de selenio más vitamina E (555 casos) o en el grupo de selenio (575 casos). La magnitud del aumento del riesgo de cáncer de próstata con vitamina E sola fue de 17%.</Strong></Para><ItemizedList id="_24" Style="simple">
     <ListItem>Diseño del estudio con  vitamina E y selenio: un ensayo aleatorizado controlado con placebo de  selenio (200 µg/d de L-selenometionina), vitamina E  (400 UI/d de todo-rac-[α]-acetato de tocoferil) o ambos.</ListItem><ListItem>Validez interna: buena.</ListItem><ListItem>Congruencia: buena.</ListItem><ListItem>Validez externa: buena.</ListItem></ItemizedList></SummarySection><ReferenceSection><Citation idx="1" PMID="20357281">Andriole GL, Bostwick DG, Brawley OW, et al.: Effect of dutasteride on the risk of prostate cancer. N Engl J Med 362 (13): 1192-202, 2010.</Citation><Citation idx="2" PMID="12824459" MedlineID="22750137">Thompson IM, Goodman PJ, Tangen CM, et al.: The influence of finasteride on the development of prostate cancer. N Engl J Med 349 (3): 215-24, 2003.</Citation><Citation idx="3" PMID="21990298">Klein EA, Thompson IM Jr, Tangen CM, et al.: Vitamin E and the risk of prostate cancer: the Selenium and Vitamin E Cancer Prevention Trial (SELECT). JAMA 306 (14): 1549-56, 2011.</Citation></ReferenceSection></SummarySection><SummarySection id="_25"><Title>Significación</Title><SummarySection id="_26"><Title>Incidencia y mortalidad</Title><Para id="_27">El carcinoma de próstata es el tumor más común en los hombres estadounidenses, con un cálculo de 220.800 casos nuevos y se 27.540 defunciones en 2015.<Reference refidx="1"/> Es notable la amplitud en el  rango de los cálculos del efecto de la enfermedad. La enfermedad es histológicamente obvia hasta en 34% de los hombres en su quinta década y hasta en 70% de los hombres de 80 años o más.<Reference refidx="2"/><Reference refidx="3"/> Se diagnosticará cáncer de próstata a casi un quinto de los hombres estadounidenses, en comparación con casi 3% de los hombres que se prevé que mueran a causa de la enfermedad.<Reference refidx="4"/> El cálculo de la reducción de la esperanza de vida de los hombres que mueren por cáncer de próstata es de aproximadamente 9 años.<Reference refidx="5"/></Para><Para id="_28">La tasa extraordinariamente alta de cáncer de próstata oculto desde el punto de vista clínico en la población general, comparada con una probabilidad 20 veces menor de muerte por la enfermedad indica que muchos de estos cánceres presentan un riesgo biológico bajo. Muchas series de pacientes con menor riesgo (es decir, tumores con puntaje de Gleason 6 y un volumen algo menor de tumores Gleason 7) de cáncer de próstata, controlados mediante vigilancia sola, con tasas de supervivencia altas a los 5 y 10 años de seguimiento se ajustan a estas observaciones.<Reference refidx="6"/> Los datos muestran, sin embargo, que con un seguimiento más largo, los cánceres de grado alto se relacionan con un mayor riesgo de muerte por cáncer de próstata.<Reference refidx="7"/><Reference refidx="8"/></Para><Para id="_29">Dada la alta variabilidad en la diferenciación tumoral de un campo microscópico a otro, muchos patólogos darán cuenta de la gama de diferenciación entre las células malignas presentes en la biopsia con el uso del sistema de gradación de Gleason.  Este sistema de gradación incluye cinco patrones histológicos que se distinguen por la arquitectura glandular del cáncer. Se identifican los patrones arquitectónicos y se les asigna un grado de 1 a 5; 1 es el grado más diferenciado y 5 el menos diferenciado. La suma de los grados del predominante y del próximo más prevalente oscilará entre 2 (tumores bien diferenciados) y 10 (tumores indiferenciados).<Reference refidx="9"/><Reference refidx="10"/> En los Estados Unidos, durante la época de la detección del antígeno prostático específico (APE) (cerca de 1985), se presentaron cambios sistemáticos en la interpretación histológica de los especímenes de biopsia, realizada por patólogos anatomistas.<Reference refidx="11"/> Este fenómeno, al que algunas veces se llama "inflación de grado", es el presunto aumento de la distribución de tumores de grado alto en la población durante un período, pero en ausencia de un cambio clínico o  biológico verdadero. Es posiblemente el resultado de un aumento en la tendencia entre los patólogos a leer el grado tumoral como más dinámico, lo que da lugar a una preponderancia mayor para tratar estos cánceres de forma intensiva.<Reference refidx="12"/></Para><Para id="_30">Entre las opciones de tratamiento disponibles para el cáncer de próstata, está la prostatectomía radical, la radioterapia de haz externo, la braquiterapia, la crioterapia, la ablación focal, la privación de andrógeno con análogos de la hormona liberadora de hormona luteinizante o antiandrógenos, la privación intermitente de andrógenos, los fármacos citotóxicos y la vigilancia activa. De todos los medios de control, solo se ha probado la prostatectomía radical  en un ensayo clínico aleatorizado, a fin de evaluar sus beneficios en cuanto a la supervivencia.  En este estudio, se encontró que la prostatectomía fue superior a la vigilancia en hombres con cáncer de próstata localizado, en términos de tasas reducidas de metástasis (riesgo relativo [RR] = 0,63; intervalo de confianza [IC] 95%, 0,41–0,96) y específico a la enfermedad (RR = 0,5; IC 95%, 0,27–0,91) y mortalidad en general.<Reference refidx="13"/> No se ha abordado de forma adecuada la eficacia relativa de la prostatectomía radical, en comparación con otras formas de tratamiento.<Reference refidx="14"/> En el tratamiento del cáncer de próstata hay asuntos confusos, como los efectos secundarios del tratamiento, la incapacidad de pronosticar la evolución natural de un cáncer dado, la comorbilidad de un paciente que podría incidir en la probabilidad individual de sobrevivir lo suficiente como para estar en riesgo de presentar morbilidad o mortalidad a causa de la enfermedad, y un volumen creciente de datos probatorios que indican que con un control específico cuidadoso del APE tras el tratamiento, una fracción sustancial de pacientes podría presentar una recidiva de la enfermedad.<Reference refidx="15"/></Para><Para id="_31">Debido a la incertidumbre considerable relacionada con la eficacia del tratamiento y la dificultad en la selección de pacientes que tienen riesgo de evolución progresiva de la enfermedad, la opinión de la comunidad médica se encuentra dividida en lo que respecta a los exámenes de detección del carcinoma de próstata. Mientras que, tanto el examen digital del recto como el de detección del APE han mostrado características razonables de eficacia (sensibilidad, especificidad y un valor predictivo positivo) para la detección temprana del cáncer de próstata, los resultados contradictorios de ensayos aleatorizados sobre el efecto de los exámenes de detección en la mortalidad han llevado a que algunas organizaciones estén a favor y otras en contra de los exámenes de detección.<Reference refidx="16"/><Reference refidx="17"/> </Para><Para id="_32">El enorme efecto del cáncer de próstata en la población estadounidense, así como la carga económica que representa esta enfermedad tanto para los pacientes como para la sociedad, han despertado un interés marcado en la prevención primaria de la enfermedad.</Para></SummarySection><ReferenceSection><Citation idx="1">American Cancer Society: Cancer Facts and Figures 2015. Atlanta, Ga: American Cancer Society, 2015. <ExternalRef xref="http://www.cancer.org/acs/groups/content/@editorial/documents/document/acspc-044552.pdf">Available online</ExternalRef>. Last accessed April 1, 2015.</Citation><Citation idx="2" PMID="8326560" MedlineID="93316369">Sakr WA, Haas GP, Cassin BF, et al.: The frequency of carcinoma and intraepithelial neoplasia of the prostate in young male patients. J Urol 150 (2 Pt 1): 379-85, 1993.</Citation><Citation idx="3" PMID="6154966" MedlineID="80191758">Hølund B: Latent prostatic cancer in a consecutive autopsy series. Scand J Urol Nephrol 14 (1): 29-35, 1980.</Citation><Citation idx="4">Altekruse SF, Kosary CL, Krapcho M, et al.: SEER Cancer Statistics Review, 1975-2007. Bethesda, Md: National Cancer Institute, 2010. <ExternalRef xref="http://seer.cancer.gov/csr/1975_2011/">Also available online</ExternalRef>.    Last accessed June 17, 2015.</Citation><Citation idx="5" PMID="2817158" MedlineID="90053911">Horm JW, Sondik EJ: Person-years of life lost due to cancer in the United States, 1970 and 1984. Am J Public Health 79 (11): 1490-3, 1989.</Citation><Citation idx="6" PMID="21825257">Cooperberg MR, Carroll PR, Klotz L: Active surveillance for prostate cancer: progress and promise. J Clin Oncol 29 (27): 3669-76, 2011.</Citation><Citation idx="7" PMID="19755699">Lu-Yao GL, Albertsen PC, Moore DF, et al.: Outcomes of localized prostate cancer following conservative management. JAMA 302 (11): 1202-9, 2009.</Citation><Citation idx="8" PMID="21751904">Jones CU, Hunt D, McGowan DG, et al.: Radiotherapy and short-term androgen deprivation for localized prostate cancer. N Engl J Med 365 (2): 107-18, 2011.</Citation><Citation idx="9" PMID="4813554" MedlineID="74102468">Gleason DF, Mellinger GT: Prediction of prognosis for prostatic adenocarcinoma by combined histological grading and clinical staging. J Urol 111 (1): 58-64, 1974.</Citation><Citation idx="10">Gleason DF: Histologic grading and clinical staging of prostatic carcinoma. In: Tannenbaum M: Urologic Pathology: The Prostate. Philadelphia, Pa: Lea and Febiger, 1977, pp 171-197.</Citation><Citation idx="11" PMID="16145045">Albertsen PC, Hanley JA, Barrows GH, et al.: Prostate cancer and the Will Rogers phenomenon. J Natl Cancer Inst 97 (17): 1248-53, 2005.</Citation><Citation idx="12" PMID="16145036">Thompson IM, Canby-Hagino E, Lucia MS: Stage migration and grade inflation in prostate cancer: Will Rogers meets Garrison Keillor. J Natl Cancer Inst 97 (17): 1236-7, 2005.</Citation><Citation idx="13" PMID="12226148" MedlineID="22213857">Holmberg L, Bill-Axelson A, Helgesen F, et al.: A randomized trial comparing radical prostatectomy with watchful waiting in early prostate cancer. N Engl J Med 347 (11): 781-9, 2002.</Citation><Citation idx="14" PMID="7500479" MedlineID="96069345">Middleton RG, Thompson IM, Austenfeld MS, et al.: Prostate Cancer Clinical Guidelines Panel Summary report on the management of clinically localized prostate cancer. The American Urological Association. J Urol 154 (6): 2144-8, 1995.</Citation><Citation idx="15" PMID="10799151" MedlineID="20259602">Moul JW: Prostate specific antigen only progression of prostate cancer. J Urol 163 (6): 1632-42, 2000.</Citation><Citation idx="16" PMID="17509297">Thompson I, Thrasher JB, Aus G, et al.: Guideline for the management of clinically localized prostate cancer: 2007 update. J Urol 177 (6): 2106-31, 2007.</Citation><Citation idx="17">Screening for Prostate Cancer. Rockville, Md: U.S. Preventive Services Task Force, 2011. <ExternalRef xref="http://www.uspreventiveservicestaskforce.org/Page/Topic/recommendation-summary/prostate-cancer-screening">Available online</ExternalRef>. Last accessed February 6, 2015.</Citation></ReferenceSection></SummarySection><SummarySection id="_87"><Title>Factores de riesgo del cáncer de próstata</Title><SummarySection id="_88"><Title>Edad</Title><Para id="_89">La incidencia del cáncer de próstata aumenta vertiginosamente  con Ia edad. Aunque es una enfermedad muy inusual en los hombres menores de 50 años, Ias tasas aumentan de forma exponencial de ahí en adelante. La tasa de registros por cohorte de edad en Inglaterra y Gales aumentó de 8 por cada mil habitantes hombres entre 50 y 56 años, a 68 por cada mil hombres entre 60 y 64 años; 260 por cada mil hombres entre 70 y 74 años, y llegó a su pico a los 406 por cada mil hombres entre 75 y 79 años.<Reference refidx="1"/> En esta misma
población, Ia tasa de muerte por cada mil en 1992 en cohortes de hombres entre
50 y 54 años, 60 y 64 años y 70 y 74 años fue de 4, 37 y	166, respectivamente.<Reference refidx="1"/> En todas las edades, Ia incidencia de cáncer de próstata en los hombres negros excedió Ia de los hombres blancos.<Reference refidx="2"/>
</Para></SummarySection><SummarySection id="_90"><Title>Antecedentes familiares</Title><Para id="_91">Cerca de 15% de quienes reciben un diagnóstico de cáncer
de próstata tienen un  pariente de primer grado (es decir, hermano, padre) con este cáncer, en comparación con aproximadamente 8% de Ia población estadounidense.<Reference refidx="3"/> Alrededor de 9% de todos los cánceres de próstata pueden ser el resultado de una susceptibilidad genética hereditaria.<Reference refidx="4"/> Varios autores han completado  análisis de segregación  y aunque se ha señalado un solo gen autosómico  muy poco común como el causante  de cáncer en algunas de estas familias,  la carga de la prueba indica que la herencia es notablemente más compleja.<Reference refidx="5"/><Reference refidx="6"/><Reference refidx="7"/>
</Para></SummarySection><SummarySection id="_92"><Title>Hormonas</Title><Para id="_93">La evolución de la próstata       depende de la secreción de   dihidrotestosterona (DHT) por los testículos del feto. La testosterona produce la virilización  normal de las estructuras  del conducto  mesonéfrico y los genitales internos, sobre la que actúa la  enzima 5-alfa reductasa (5AR)
para formar la DHT. La DHT tiene una afinidad 4
a   50 veces mayor con el receptor de andrógeno que
con la testosterona.  La DHT es la que permite  la evolución  normal de la próstata.  Los niños que nacen con 5AR anómala  (debido a un cambio en uno de los pares básicos del   exón 5 del tipo de gen normal II 5AR) presentan genitales  ambiguos (que se describen de formas diversas como hipospadias  con una vagina ciega a un falo pequeño),  pero se masculinizan  durante la pubertad  a causa del surgimiento  de la producción  de testosterona  en ese momento.  En los estudios clínicos, imaginológicos  e histológicos  de parientes nacidos con deficiencia  de 5AR, se  ha mostrado  una próstata  pequeña  con apariencia de panqueque con      concentraciones  de antígeno  prostático específico  (APE) indetectables  y ausencia  de epitelio  prostático.<Reference refidx="8"/>  El seguimiento  a largo plazo no muestra el surgimiento  de hiperplasia  prostática benigna (HPB) ni de cáncer de próstata.</Para><Para id="_94">Otras pruebas, como las siguientes,  indican que el grado de exposición
 
acumulada  de la próstata a los andrógenos   se  relaciona con un aumento del riesgo de cáncer de próstata:
</Para><OrderedList id="_95" Style="Arabic" Compact="No">
     <ListItem>No se tienen  informes de que se haya presentado  cáncer de próstata  ni HPB en los hombres castrados  antes de la pubertad.<Reference refidx="9"/></ListItem><ListItem>La privación  de andrógeno  en casi todas sus formas conlleva  la involución  de la próstata, el descenso  en las concentraciones  de APE, la apoptosis  de las células de cáncer de próstata y células epiteliales,  y la respuesta clínica en los pacientes de cáncer de
próstata.<Reference refidx="10"/><Reference refidx="11"/></ListItem><ListItem>Los resultados  de dos ensayos  de quimioprevención  a gran escala del uso de inhibidores  de 5AR (finasterida  y dutasterida) mostraron que los andrógenos  intraprostáticos  modulan el riesgo de cáncer          de próstata.  En ambos estudios,  se identificaron reducciones

del riesgo de cáncer de próstata en general, aunque con un aumento de riesgo de la enfermedad  de grado alto.<Reference refidx="12"/><Reference refidx="13"/></ListItem></OrderedList><Para id="_96">En estudios ecológicos, se observó   una correlación  entre las concentraciones  séricas de testosterona, principalmente  DHT y   el riesgo general de cáncer de próstata entre los hombres afroamericanos,   blancos y japoneses.<Reference refidx="14"/><Reference refidx="15"/><Reference refidx="16"/>  Sin embargo,  hay pruebas provenientes  de estudios  prospectivos  sobre la relación entre las concentraciones  séricas de hormonas  sexuales,  como andrógenos  y estrógenos,
que no sustentan  un vínculo  directo.<Reference refidx="17"/> En un análisis colaborativo  de 18 estudios  prospectivos  que comprendió  las medidas prediagnósticas  en
3.886 hombres con cáncer de próstata  incidental  y 6.438 sujetos de control,  no se encontró  relación entre el riesgo de cáncer de próstata y las concentraciones  séricas de testosterona,  testosterona  libre calculada, sulfato de hidrotestosterona,  androstenediona,   glucorónido de androstanediol, glucurónido, estradiol  o estradiol libre   calculado.<Reference refidx="17"/>    Hay que tener precaución  al
interpretar  los datos, dado el desconocimiento  del grado de correlación entre las concentraciones  séricas y las concentraciones  tisulares prostáticas. El glucurónido de androstanediol  podría  reflejar de forma más cercana  una actividad  androgénica  intraprostática,  y esta medida  no se relacionó  con el riesgo de cáncer de próstata. Esta falta de relación  confirma que la estratificación  del riesgo no se puede realizar en las concentraciones   séricas hormonales.
</Para></SummarySection><SummarySection id="_97"><Title>Raza</Title><Para id="_98">EI riesgo de presentar  cáncer de próstata y morir por esta causa es significativamente   mayor entre los hombres negros, entre los hombres blancos, este riesgo es intermedio y los japoneses nativos tienen el riesgo más bajo.<Reference refidx="18"/><Reference refidx="19"/>   Se han publicado  datos   contradictorios  con relación a la etiología  de estos resultados,  pero hay ciertas pruebas que dan cuenta de que el acceso a los cuidados de salud puede incidir en el desenlace de la enfermedad.<Reference refidx="20"/></Para></SummarySection><SummarySection id="_99"><Title>Grasa alimenticia</Title><Para id="_100">Una observación  interesante es que la incidencia   de cáncer de
próstata  latente (oculto, histológicamente  comprobable)  es similar en todo el mundo, el cáncer de próstata  clínico  varía de país a país hasta en  20 veces.<Reference refidx="21"/> En estudios ecológicos  previos, se mostró  un vínculo   directo entre la tasa de mortalidad  específica   al cáncer de próstata en un país dado y el promedio  de calorías
totales provenientes   de la grasa que consume  la población de ese país.<Reference refidx="22"/><Reference refidx="23"/> Los estudios sobre inmigrantes japoneses dan   muestra de que los nativos del Japón tienen el riesgo más bajo de cáncer de próstata clínico,  los estadounidenses de origen japonés de primera generación  tienen un riesgo
intermedio y las generaciones  siguientes  tienen un riesgo comparable  con el de la población  de los Estados  Unidos.<Reference refidx="24"/><Reference refidx="25"/> Los modelos animales  a los que se les implantó cáncer de próstata  humano mostraron  una disminución  de las tasas de crecimiento  tumoral en aquellos animales  a los que se les alimenta  con una dieta baja en grasa.<Reference refidx="26"/><Reference refidx="27"/> Pruebas provenientes  de muchos estudios de casos y controles muestran  una relación entre la grasa alimenticia  y el riesgo de cáncer de próstata,<Reference refidx="28"/><Reference refidx="29"/><Reference refidx="30"/> aunque los estudios no han llegado a esta conclusión de forma unánime.<Reference refidx="31"/><Reference refidx="32"/><Reference refidx="33"/> En una revisión de los estudios  publicados  sobre la relación entre las grasas alimenticias  y el riesgo de cáncer de próstata, entre los estudios descriptivos,  aproximadamente   la mitad encontró que el riesgo aumenta ante el incremento  de la ingesta de grasas alimenticias,  grasas animales  y grasas saturadas  y monoinsaturadas,  mientras que   la otra mitad no encontró  ninguna
relación.<Reference refidx="34"/> Entre los estudios de casos y controles, en cerca de la mitad se encontró un mayor riesgo con el aumento del consumo de grasas alimenticias, grasas animales y grasas saturadas y monoinsaturadas; aproximadamente la otra mitad no encontró ninguna relación. Solo en los estudios de ingesta de grasas polinsaturadas, se encontraron tres estudios que informaron sobre        una relación significativamente
negativa entre el cáncer de próstata y la ingesta de grasa. Las grasas de
origen animal  parecen estar relacionadas  con un riesgo mayor.<Reference refidx="20"/><Reference refidx="35"/> En una serie con 384 pacientes de cáncer de próstata, el riesgo de evolución  de cáncer a un estadio  más avanzado  fue mayor en hombres con una ingesta alta de grasa.<Reference refidx="36"/> El anuncio en 1996 que informó de la disminución de las tasas de mortalidad por cáncer en los Estados Unidos dio origen al señalamiento de que esta se debió a la disminución en la ingesta de grasas alimenticias durante el mismo período.<Reference refidx="37"/><Reference refidx="38"/></Para><Para id="_101">Se llevaron a cabo dos estudios dentro del  Prostate Prevention
Trial,  en los que se recopiló  información sobre nutrición y a todos los sujetos se les recomendó someterse    a una biopsia.  Los hallazgos incluyeron  que entre 9.559 sujetos, no hubo relación entre ningún complemento o nutriente  (incluyendo    la grasa) y el riesgo de cáncer de próstata en general,  pero el riesgo   de cáncer de grado alto se vio vinculado  con una ingesta elevada de grasas polinsaturadas.  En un subconjunto  de 1.658
casos y 1.803 controles, se examinaron  ácidos grasos específicos  y el ácido docosahexaenóico   se relacionó con el riesgo de enfermedad  de grado alto, mientras que los ácidos grasos trans (TFA) 18:1 y TFA 18:2 estuvieron  inversamente  relacionados  con riesgo de enfermedad  de
grado alto. Estos estudios  numerosos  a gran escala indican una relación  compleja  entre nutrientes como las grasas y el riesgo de cáncer de próstata.<Reference refidx="39"/><Reference refidx="40"/></Para><Para id="_102">No se cuenta con una explicación  de la presunta relación entre el cáncer de próstata y las grasas alimenticias.  Han surgido  varias hipótesis,  como las siguientes:</Para><OrderedList id="_103" Style="Arabic" Compact="No">
     <ListItem>Las grasas alimenticias  pueden aumentar  las concentraciones séricas de andrógeno  y, por tanto, aumentar  el riesgo de cáncer de próstata.  Esta hipótesis se sustenta en las observaciones  en Sudáfrica y los Estados Unidos de que los cambios en la ingesta de grasas alimenticias  modifica las concentraciones  séricas y urinarias de andrógeno.<Reference refidx="41"/><Reference refidx="42"/></ListItem><ListItem>Ciertos tipos de ácidos grasos   o sus metabolitos  podrían  iniciar o promover  la aparición  del carcinoma  de próstata.  Las pruebas de esta hipótesis son contradictorias,       pero un estudio  indica que el ácido linoléico  (ácido graso polinsaturado omega-6)  podría estimular  el
crecimiento  de células cancerosas,  mientras que el ácido graso
omega 3 inhibe  el crecimiento  celular.<Reference refidx="43"/></ListItem><ListItem>Una observación     realizada en modelos  animales es que las crías
machos  de ratas preñadas  a las que se   suministra  una dieta de alto contenido graso presentarán  cáncer en una tasa más alta que los animales  a los que se Ies suministra una dieta  baja en grasa.<Reference refidx="44"/> Esta observación  podría  explicar algunas  de las variaciones  en
la incidencia  del cáncer de próstata y su mortalidad  entre
grupos étnicos;  se ha observado  que durante el primer trimestre  de embarazo de las mujeres negras,  las concentraciones  de andrógeno  son mayores que las de las mujeres blancas.<Reference refidx="45"/>
</ListItem></OrderedList></SummarySection><SummarySection id="_104"><Title>Ingesta de lácteos  y calcio                </Title><Para id="_105">En un metanálisis de diez estudios de cohortes  (ocho estadounidenses  y dos europeos), se concluyó  que los hombres con la ingesta más alta de productos  lácteos (riesgo relativo [RR] = 1,11; intervalo de confianza  [IC]
95%, 1,00–1,22;  <Emphasis>P</Emphasis> = 0,004) y calcio (RR = 1,39;  IC 95%,  1,09–1,77;  <Emphasis>P</Emphasis> =
0,18) tuvieron  una mayor probabilidad  de presentar cáncer de próstata
que los hombres con la menor ingesta.  Los RR conjuntos  de cáncer de próstata avanzado fueron de 1,33 (IC 95% , 1,00–1,78;  <Emphasis>P</Emphasis> = 0,055) para la ingesta más alta comparada con la más baja en las categorías  de productos
lácteos, y 1,46 (IC 95%,     0,65–3,25;   <Emphasis>P</Emphasis> &gt; 0,2) para la ingesta más alta versus  las más baja de calcio. La ingesta alta de productos  lácteos y calcio podría relacionarse  con un aumento de riesgo de cáncer de próstata, aunque el aumento  podría ser pequeño.<Reference refidx="46"/></Para></SummarySection><SummarySection id="_106"><Title>Uso de multivitamínicos</Title><Para id="_107">EI uso regular de multivitamínicos   no se ha vinculado  con el riesgo de cáncer de próstata  inicial o localizado.  Sin embargo,  en este estudio numeroso  (295,344  hombres)  hubo un aumento estadísticamente  significativo del riesgo de cáncer de próstata avanzado  mortal entre  los hombres con uso excesivo  de multivitamínicos.<Reference refidx="47"/></Para></SummarySection><SummarySection id="_108"><Title>Folato</Title><Para id="_109">EI Aspirin/Folate Polyp Prevention Study,                                        un ensayo aleatorizado,  controlado  con placebo, complementado con Aspirina  y ácido fólico para la quimioprevención  de los adenomas  colorrectales,  se llevó a cabo entre el 6   de julio de 1994 y el 31 de diciembre  de 2006.  En un análisis secundario,  los autores abordaron  el efecto de los complementos  de ácido fólico en el riesgo de cáncer de próstata. A los participantes  se les dio seguimiento  hasta por 10,8 años (mediana = 7,0, rango intercuartil  = 6,0–7,8)  y se les pidió que  informaran  periódicamente sobre sus
enfermedades  y hospitalizaciones.<Reference refidx="48"/>   La complementación  con 1 mg de
ácido fólico se relacionó con un aumento del riesgo de cáncer de próstata. Sin embargo,  las concentraciones  alimentarias y plasmáticas entre los que
no usaron multivitamínicos  fueron  inversamente proporcionales                 al riesgo. Estos hallazgos  resaltan la función  potencialmente  compleja  de los folatos en la carcinogenia  prostática.<Reference refidx="48"/><Reference refidx="49"/></Para></SummarySection><SummarySection id="_110"><Title>Exposición al cadmio</Title><Para id="_111">La exposición  al cadmio es de tipo ocupacional  y se relaciona con las plantas de recuperación  de níquel y cadmio a partir de las baterías,
también se relaciona con el consumo de cigarrillo.<Reference refidx="50"/> Los estudios  iniciales de estas sustancia  documentaron  un vínculo  aparente,  pero estudios
mejor  diseñados  no han logrado notar dicha relación.<Reference refidx="51"/><Reference refidx="52"/></Para></SummarySection><SummarySection id="_112"><Title>Exposición a la dioxina</Title><Para id="_113">La dioxina  (2,3,7,8-tetraclorodibenzo-p-dioxina o TCDD es un contaminante  de un herbicida que se usó en Vietnam.  Este químico  es similar a muchos  de los componentes  de los herbicidas  que se usan en la agricultura.  En una revisión del vínculo  entre la dioxina y el
riesgo de cáncer de próstata  realizada por la National Academy  of Sciences  Institute of Medicine Committee  to Review the Health Effects in Vietnam Veterans  of Exposure to Herbicides,  se encontraron  solo dos artículos sobre cáncer de próstata con el suficiente  número de casos y
seguimiento  como para permitir el análisis.<Reference refidx="53"/><Reference refidx="54"/> EI análisis de todos
los datos disponibles  indica que la relación entre la exposición  a la dioxina y el cáncer de próstata  no es concluyente.<Reference refidx="55"/></Para></SummarySection><ReferenceSection><Citation idx="1">Epidemiological aspects. In: Kirby RS, Christmas TJ, Brawer MK: Prostate Cancer. London, England: Mosby, 1996, pp 23-32.</Citation><Citation idx="2">Cancer incidence in the United States (SEER) age-specific rates. In: Harras A, Edwards BK, Blot WJ, eds.: Cancer Rates and Risks. 4th ed. Bethesda, Md: National Cancer Institute, 1996, pp 22.</Citation><Citation idx="3" PMID="2251225" MedlineID="91067587">Steinberg GD, Carter BS, Beaty TH, et al.: Family history and the risk of prostate cancer. Prostate 17 (4): 337-47, 1990.</Citation><Citation idx="4" PMID="9333266" MedlineID="97472441">Grönberg H, Isaacs SD, Smith JR, et al.: Characteristics of prostate cancer in families potentially linked to the hereditary prostate cancer 1 (HPC1) locus. JAMA 278 (15): 1251-5, 1997.</Citation><Citation idx="5" PMID="1841757" MedlineID="93046220">Carter BS, Steinberg GD, Beaty TH, et al.: Familial risk factors for prostate cancer. Cancer Surv 11: 5-13, 1991.</Citation><Citation idx="6" PMID="9585590" MedlineID="98254463">Schaid DJ, McDonnell SK, Blute ML, et al.: Evidence for autosomal dominant inheritance of prostate cancer. Am J Hum Genet 62 (6): 1425-38, 1998.</Citation><Citation idx="7" PMID="9609635" MedlineID="98270798">Bauer JJ, Srivastava S, Connelly RR, et al.: Significance of familial history of prostate cancer to traditional prognostic variables, genetic biomarkers, and recurrence after radical prostatectomy. Urology 51 (6): 970-6, 1998.</Citation><Citation idx="8" PMID="1400866" MedlineID="93016613">Imperato-McGinley J, Gautier T, Zirinsky K, et al.: Prostate visualization studies in males homozygous and heterozygous for 5 alpha-reductase deficiency. J Clin Endocrinol Metab 75 (4): 1022-6, 1992.</Citation><Citation idx="9" PMID="1289665" MedlineID="93172728">Isaacs JT: Hormonal balance and the risk of prostatic cancer. J Cell Biochem Suppl 16H: 107-8, 1992.</Citation><Citation idx="10" PMID="2441256" MedlineID="87287077">Peters CA, Walsh PC: The effect of nafarelin acetate, a luteinizing-hormone-releasing hormone agonist, on benign prostatic hyperplasia. N Engl J Med 317 (10): 599-604, 1987.</Citation><Citation idx="11" PMID="2608047" MedlineID="90114152">Kyprianou N, Isaacs JT: Expression of transforming growth factor-beta in the rat ventral prostate during castration-induced programmed cell death. Mol Endocrinol 3 (10): 1515-22, 1989.</Citation><Citation idx="12" PMID="20357281">Andriole GL, Bostwick DG, Brawley OW, et al.: Effect of dutasteride on the risk of prostate cancer. N Engl J Med 362 (13): 1192-202, 2010.</Citation><Citation idx="13" PMID="12824459" MedlineID="22750137">Thompson IM, Goodman PJ, Tangen CM, et al.: The influence of finasteride on the development of prostate cancer. N Engl J Med 349 (3): 215-24, 2003.</Citation><Citation idx="14" PMID="1621259" MedlineID="92320557">Ellis L, Nyborg H: Racial/ethnic variations in male testosterone levels: a probable contributor to group differences in health. Steroids 57 (2): 72-5, 1992.</Citation><Citation idx="15" PMID="1348296" MedlineID="92212000">Ross RK, Bernstein L, Lobo RA, et al.: 5-alpha-reductase activity and risk of prostate cancer among Japanese and US white and black males. Lancet 339 (8798): 887-9, 1992.</Citation><Citation idx="16" PMID="8672990" MedlineID="96114049">Wu AH, Whittemore AS, Kolonel LN, et al.: Serum androgens and sex hormone-binding globulins in relation to lifestyle factors in older African-American, white, and Asian men in the United States and Canada. Cancer Epidemiol Biomarkers Prev 4 (7): 735-41, 1995 Oct-Nov.</Citation><Citation idx="17" PMID="18230794">Roddam AW, Allen NE, Appleby P, et al.: Endogenous sex hormones and prostate cancer: a collaborative analysis of 18 prospective studies. J Natl Cancer Inst 100 (3): 170-83, 2008.</Citation><Citation idx="18">Altekruse SF, Kosary CL, Krapcho M, et al.: SEER Cancer Statistics Review, 1975-2007. Bethesda, Md: National Cancer Institute, 2010. <ExternalRef xref="http://seer.cancer.gov/csr/1975_2011/">Also available online</ExternalRef>.    Last accessed June 17, 2015.</Citation><Citation idx="19" PMID="12163325" MedlineID="22153054">Bunker CH, Patrick AL, Konety BR, et al.: High prevalence of screening-detected prostate cancer among Afro-Caribbeans: the Tobago Prostate Cancer Survey. Cancer Epidemiol Biomarkers Prev 11 (8): 726-9, 2002.</Citation><Citation idx="20" PMID="7474244" MedlineID="96074260">Optenberg SA, Thompson IM, Friedrichs P, et al.: Race, treatment, and long-term survival from prostate cancer in an equal-access medical care delivery system. JAMA 274 (20): 1599-605, 1995 Nov 22-29.</Citation><Citation idx="21" PMID="5109447" MedlineID="71278291">Wynder EL, Mabuchi K, Whitmore WF Jr: Epidemiology of cancer of the prostate. Cancer 28 (2): 344-60, 1971.</Citation><Citation idx="22" PMID="1140864" MedlineID="75188648">Armstrong B, Doll R: Environmental factors and cancer incidence and mortality in different countries, with special reference to dietary practices. Int J Cancer 15 (4): 617-31, 1975.</Citation><Citation idx="23" PMID="1435098" MedlineID="93061750">Rose DP, Connolly JM: Dietary fat, fatty acids and prostate cancer. Lipids 27 (10): 798-803, 1992.</Citation><Citation idx="24" PMID="5635018" MedlineID="68095910">Haenszel W, Kurihara M: Studies of Japanese migrants. I. Mortality from cancer and other diseases among Japanese in the United States. J Natl Cancer Inst 40 (1): 43-68, 1968.</Citation><Citation idx="25" PMID="2069852" MedlineID="91299495">Shimizu H, Ross RK, Bernstein L, et al.: Cancers of the prostate and breast among Japanese and white immigrants in Los Angeles County. Br J Cancer 63 (6): 963-6, 1991.</Citation><Citation idx="26" PMID="7545759" MedlineID="95404646">Wang Y, Corr JG, Thaler HT, et al.: Decreased growth of established human prostate LNCaP tumors in nude mice fed a low-fat diet. J Natl Cancer Inst 87 (19): 1456-62, 1995.</Citation><Citation idx="27" PMID="9427973" MedlineID="98089442">Connolly JM, Coleman M, Rose DP: Effects of dietary fatty acids on DU145 human prostate cancer cell growth in athymic nude mice. Nutr Cancer 29 (2): 114-9, 1997.</Citation><Citation idx="28" PMID="3471995" MedlineID="87199593">Ross RK, Shimizu H, Paganini-Hill A, et al.: Case-control studies of prostate cancer in blacks and whites in southern California. J Natl Cancer Inst 78 (5): 869-74, 1987.</Citation><Citation idx="29" PMID="3358418" MedlineID="88191882">Kolonel LN, Yoshizawa CN, Hankin JH: Diet and prostatic cancer: a case-control study in Hawaii. Am J Epidemiol 127 (5): 999-1012, 1988.</Citation><Citation idx="30" PMID="7752270" MedlineID="95271698">Whittemore AS, Kolonel LN, Wu AH, et al.: Prostate cancer in relation to diet, physical activity, and body size in blacks, whites, and Asians in the United States and Canada. J Natl Cancer Inst 87 (9): 652-61, 1995.</Citation><Citation idx="31">Giovannucci E: Epidemiologic characteristics of prostate cancer. Cancer  75 (Suppl 7): 1766-77, 1995.</Citation><Citation idx="32" PMID="2743255" MedlineID="89303713">Mettlin C, Selenskas S, Natarajan N, et al.: Beta-carotene and animal fats and their relationship to prostate cancer risk. A case-control study. Cancer 64 (3): 605-12, 1989.</Citation><Citation idx="33" PMID="2924323" MedlineID="89168234">Severson RK, Nomura AM, Grove JS, et al.: A prospective study of demographics, diet, and prostate cancer among men of Japanese ancestry in Hawaii. Cancer Res 49 (7): 1857-60, 1989.</Citation><Citation idx="34" PMID="9394717" MedlineID="98056699">Zhou JR, Blackburn GL: Bridging animal and human studies: what are the missing segments in dietary fat and prostate cancer? Am J Clin Nutr 66 (6 Suppl): 1572S-1580S, 1997.</Citation><Citation idx="35" PMID="3768832" MedlineID="87027938">Rose DP, Boyar AP, Wynder EL: International comparisons of mortality rates for cancer of the breast, ovary, prostate, and colon, and per capita food consumption. Cancer 58 (11): 2363-71, 1986.</Citation><Citation idx="36" PMID="9507851" MedlineID="98167269">Bairati I, Meyer F, Fradet Y, et al.: Dietary fat and advanced prostate cancer. J Urol 159 (4): 1271-5, 1998.</Citation><Citation idx="37" PMID="8918396" MedlineID="97076073">Cole P, Rodu B: Declining cancer mortality in the United States. Cancer 78 (10): 2045-8, 1996.</Citation><Citation idx="38" PMID="9048839" MedlineID="97201010">Wynder EL, Cohen LA: Correlating nutrition to recent cancer mortality statistics. J Natl Cancer Inst 89 (4): 324, 1997.</Citation><Citation idx="39" PMID="21335507">Kristal AR, Till C, Platz EA, et al.: Serum lycopene concentration and prostate cancer risk: results from the Prostate Cancer Prevention Trial. Cancer Epidemiol Biomarkers Prev 20 (4): 638-46, 2011.</Citation><Citation idx="40" PMID="20693267">Kristal AR, Arnold KB, Neuhouser ML, et al.: Diet, supplement use, and prostate cancer risk: results from the prostate cancer prevention trial. Am J Epidemiol 172 (5): 566-77, 2010.</Citation><Citation idx="41" PMID="498137" MedlineID="80044774">Hill P, Wynder EL, Garbaczewski L, et al.: Diet and urinary steroids in black and white North American men and black South African men. Cancer Res 39 (12): 5101-5, 1979.</Citation><Citation idx="42" PMID="6538617" MedlineID="84166306">Hämäläinen E, Adlercreutz H, Puska P, et al.: Diet and serum sex hormones in healthy men. J Steroid Biochem 20 (1): 459-64, 1984.</Citation><Citation idx="43" PMID="2020620" MedlineID="91212303">Rose DP, Connolly JM: Effects of fatty acids and eicosanoid synthesis inhibitors on the growth of two human prostate cancer cell lines. Prostate 18 (3): 243-54, 1991.</Citation><Citation idx="44" PMID="7525054" MedlineID="95042365">Kondo Y, Homma Y, Aso Y, et al.: Promotional effect of two-generation exposure to a high-fat diet on prostate carcinogenesis in ACI/Seg rats. Cancer Res 54 (23): 6129-32, 1994.</Citation><Citation idx="45" PMID="3358915" MedlineID="88193051">Henderson BE, Bernstein L, Ross RK, et al.: The early in utero oestrogen and testosterone environment of blacks and whites: potential effects on male offspring. Br J Cancer 57 (2): 216-8, 1988.</Citation><Citation idx="46" PMID="16333032">Gao X, LaValley MP, Tucker KL: Prospective studies of dairy product and calcium intakes and prostate cancer risk: a meta-analysis. J Natl Cancer Inst 97 (23): 1768-77, 2005.</Citation><Citation idx="47" PMID="17505071">Lawson KA, Wright ME, Subar A, et al.: Multivitamin use and risk of prostate cancer in the National Institutes of Health-AARP Diet and Health Study. J Natl Cancer Inst 99 (10): 754-64, 2007.</Citation><Citation idx="48" PMID="19276452">Figueiredo JC, Grau MV, Haile RW, et al.: Folic acid and risk of prostate cancer: results from a randomized clinical trial. J Natl Cancer Inst 101 (6): 432-5, 2009.</Citation><Citation idx="49" PMID="19276449">Kristal AR, Lippman SM: Nutritional prevention of cancer: new directions for an increasingly complex challenge. J Natl Cancer Inst 101 (6): 363-5, 2009.</Citation><Citation idx="50">Pienta KJ: Epidemiology and etiology of prostate cancer. In: Raghavan D, Scher HI, Leibel SA, eds.: Principles and Practice of Genitourinary Oncology. Philadelphia, Pa: Lippincott-Raven Publishers, 1997, pp 379-385.</Citation><Citation idx="51" PMID="1615308" MedlineID="92311636">García Sánchez A, Antona JF, Urrutia M: Geochemical prospection of cadmium in a high incidence area of prostate cancer, Sierra de Gata, Salamanca, Spain. Sci Total Environ 116 (3): 243-51, 1992.</Citation><Citation idx="52">Boffetta P: Methodological aspects of the epidemiological association between cadmium and cancer in humans. In: Nordberg GF, Herber RF, Alessio L, eds.: Cadmium in the Human Environment: Toxicity and Carcinogenicity. Lyon, France: International Agency for Research on Cancer, 1992, pp 425-434.</Citation><Citation idx="53" PMID="1985242" MedlineID="91087887">Fingerhut MA, Halperin WE, Marlow DA, et al.: Cancer mortality in workers exposed to 2,3,7,8-tetrachlorodibenzo-p-dioxin. N Engl J Med 324 (4): 212-8, 1991.</Citation><Citation idx="54" PMID="2729256" MedlineID="89270437">Bertazzi PA, Zocchetti C, Pesatori AC, et al.: Ten-year mortality study of the population involved in the Seveso incident in 1976. Am J Epidemiol 129 (6): 1187-200, 1989.</Citation><Citation idx="55">Committee to Review the Health Effects in Vietnam Veterans of Exposure to Herbicides: Veterans and Agent Orange: Update 1996. In: Washington DC, National Academy Press, 1996.</Citation></ReferenceSection></SummarySection><SummarySection id="_114"><Title>Oportunidades para la prevención
</Title><SummarySection id="_137"><Title>Prevención hormonal</Title><Para id="_116">EI Prostate Cancer  Prevention  Trial (PCPT), un ensayo  numeroso, aleatorizado,  controlado  con  placebo, de finasterida  (un inhibidor de la reductasa α), que contó con la participación de 18.882 hombres de 55 años o  más. A los 7 años, la incidencia  del cáncer de próstata fue de 18,4% en el grupo
de finasterida,  comparado con  24,4% en el grupo de placebo,  con una reducción  relativa del riesgo (RRR) de  24,8% (intervalo de confianza  [IC] 95%,
18,6-30,6%;  <Emphasis>P</Emphasis> &lt; 0,001). EI grupo de finasterida  contó con   más pacientes  con puntaje de Gleason  7 a 10, pero la importancia  clínica del puntaje de Gleason resulta incierta en condiciones  de privación de andrógeno.<Reference refidx="1"/>  Se observaron cánceres  de grado alto en 6,4 %        de los pacientes  del grupo de finasterida,  en comparación  con 5,1%    de los hombres que recibieron  placebo.  EI aumento  de tumores de grado alto se presentó en el trascurso de 1 año de exposición  a la finasterida y no aumentó durante este
período.<Reference refidx="2"/></Para><Para id="_117">La finasterida  disminuye  el riesgo de cáncer de próstata, pero también puede alterar la detección  de la enfermedad  a través de los efectos en el antígeno prostático específico   (APE), el examen digital del recto y la disminución  del volumen  prostático  (24%), lo que crea un sesgo de detección.<Reference refidx="3"/>  EI ajuste del APE en los hombres que toman finasterida  preserva  las funciones características  de la detección  del cáncer.<Reference refidx="4"/></Para><Para id="_118">Es posible que la finasterida  haya inducido la aparición  de una neoplasia epitelial de grado alto, pero esto no se ha demostrado.<Reference refidx="3"/> Con la aparición  de cáncer de próstata de grado alto inducido por la finasterida, se hubiese esperado  un aumento  gradual y progresivo  en el número de tumores  de grado alto por más de 7 años, en comparación  con el placebo; sin embargo,  este no fue el caso. EI aumento de tumores de
grado alto se vio durante un año de exposición  a la finasterida  y
no aumentó durante ese período.<Reference refidx="2"/> En un análisis de los datos del PCPT
ajustados  mediante fuentes de sesgo de detección,  se encontró  que la finasterida  redujo la incidencia de cáncer de próstata con puntajes de Gleason 5 a 7 y Gleason 3 a 4, pero no de Gleason  8 a 10. La reducción
de la incidencia  de Gleason 7 (22%) fue menor que la reducción en la incidencia de Gleason  5 (58%) y Gleason 6 (52%).<Reference refidx="5"/>   En un análisis en el que se usaron metodologías  diferentes, se encontró  una reducción general tanto de los cánceres  de grado bajo (Gleason &lt;6) como los de grado alto (Gleason
&gt;7).<Reference refidx="6"/></Para><Para id="_119">En eI ensayo  Reduction  by Dutasteride  of Prostate Cancer Events, se asignó al azar  a 8.231 hombres entre 50 y 75 años con riesgo alto de cáncer de próstata  (es decir, APE 2,5-10,0),  con una
biopsia negativa reciente de próstata  a recibir 0,5 mg diarios de dutasterida o placebo.  EI criterio de valoración  primario fue el cáncer de próstata diagnosticado  mediante  biopsia prostática a los 2  y 4 años después  de la aleatorización.  Luego de 4 años, entre los 6.729 hombres  (82% de la población inicial) que se sometieron    al menos a una biopsia  prostática, 25,1% en el grupo de placebo y 19,9%        en el grupo de dutasterida  habían sido diagnosticados  con cáncer de próstata,  una diferencia  estadísticamente   significativa  (reducción absoluta del riesgo  =
5,1%        y RRR = 22,8% [IC 95%, 15,2-29,8%]).     EI RRR entre el tercer y
cuarto año fue similar al RRR entre el primer y el segundo  año. La diferencia  entre los grupos se debió totalmente a una reducción  del cáncer de próstata  con un puntaje de Gleason 5 a 7. Entre los años 3 y
4 hubo un aumento  estadísticamente   significativo  en el grupo de dutasterida,  en comparación  con el grupo de placebo de cánceres  de próstata  con puntaje de Gleason 8 a 10 (12 cánceres  en el grupo de
dutasterida  vs. 1 cáncer el grupo de placebo).<Reference refidx="7"/></Para><Para id="_120">En general,  no hubo diferencia  estadísticamente  significativa  entre los tumores  de grado alto para los cánceres  con puntaje de Gleason 8 a 10 en el primer y cuarto año (29 vs. 19; 0,9  vs. 0,6%;     <Emphasis>P</Emphasis> = 0,15). Sin embargo,  en un análisis  retrospectivo,  hubo una diferencia  estadísticamente  significativa entre el tercer y cuarto año. Dado que este es un subgrupo  retrospectivo pequeño,  el hallazgo de un aumento  en los cánceres con puntaje de Gleason 8 a 10 es de validez  incierta. Sin embargo,  el hallazgo de que estos cánceres
no se redujeron es más significativo.<Reference refidx="7"/></Para><Para id="_121">Hay varias explicaciones  plausibles para la falla  de la respuesta a la finasterida  o la dutasterida  en la reducción de  la incidencia  de cánceres  con puntaje de Gleason 8 a 10. Debido a esta incertidumbre, en la actualidad, las pruebas son insuficientes  para determinar  el efecto profiláctico  de estos medicamentos  en la mortalidad por cáncer de próstata.</Para><Para id="_122">Los fármacos  que se usan en el tratamiento  hormonal de los cánceres  de próstata  actuales  resultarían  inadecuados  para la quimioprevención   del cáncer de próstata debido al costo y la amplia gama de efectos secundarios,  como disfunción  sexual, osteoporosis        y síntomas vasomotores  (sofocos).<Reference refidx="8"/>  Los antiandrógenos  más recientes  pueden
desempeñar  una función  preventiva  en el futuro.<Reference refidx="9"/></Para><Para id="_123">En una revisión sistemática  de Cochrane  de todos los estudios publicados de las investigaciones  de los resultados clínicos de los efectos
preventivos  para la próstata de los inhibidores  de la 5-alfa reductasa (5AR)
durante  el 2010 que se mantuvieron  por lo menos durante  un año,
se concluyó  que la finasterida  y la dutasterida  reducen el riesgo de recibir un diagnóstico de cáncer de próstata  entre los hombres que se someten  habitualmente a exámenes  de detección  del cáncer de próstata.  La revisión también  concluyó  que los efectos en la mortalidad  no pudieron  evaluarse  a partir de estos estudios y que el uso persistente  de estos fármacos  aumentó  la disfunción  sexual y eréctil. La revisión se sustentó en las búsquedas  computarizadas  realizadas en   MEDLINE y Cochrane  Collaboration  Library durante junio de 2010, mediante el uso de términos  del Medical Subject Headings y las palabras  'finasterida', 'dutasterida',  'neoplasias', 'azasteroides',   'inhibidores  de la reductasa'  e 'inhibidores  de enzimas',  a fin de identificar ensayos aleatorizados.  Ocho estudios  cumplieron  con los criterios de inclusión.  Solo el Prostate Cáncer Prevention  Trial y el Reduction  by Dutasteride of Prostate Cancer Events se diseñaron  para evaluar  el efecto de
los inhibidores  de la 5AR en el período de prevalencia  del cáncer de próstata. En una revisión  de estos ocho estudios, se concluyó  que, en comparación  con el placebo,  los inhibidores  de la 5AR redujeron en 25% el riesgo relativo (RR) de los cánceres de próstata detectados  "por causa'' (RR =
0,75; IC 95%, 0,67–-0,83  y 1,4% de reducción absoluta  del riesgo [3,5 vs.
4,9%]). En seis ensayos de inhibidores  de la 5AR versus placebo, se evaluaron los cánceres  de próstata detectados  en general.  Entre estos, hubo una reducción  del RR de 26% que favoreció  a los inhibidores  de 5AR (RR =
0,74; IC 95%, 0,55–1,00 y  2,9% reducción de riesgo absoluto [6,3 vs.
9,2%]).      Hubo reducciones  que trascendieron la edad, la raza y los antecedentes familiares.  En un ensayo controlado  con  placebo de hombres considerados  con un mayor riesgo de cáncer de próstata según la edad, un APE elevado y la presunción  previa de cáncer de próstata que conllevó a una biopsia de próstata, se informó que la dutasterida  no redujo los cánceres de próstata  que se identificaron por causa con base en la biopsia con aguja, pero sí redujo el riesgo general de un incidente de cáncer de próstata detectado  por biopsia en 23%    (RR = 0,77;   IC 95%,     0,7–0,85  y reducción absoluta del riesgo  16,1 vs. 20,8%).  Hubo reducciones  que trascendieron  la edad, los antecedentes  familiares de cáncer de próstata,  las concentraciones  de APE, y los subgrupos  de volúmenes  prostáticos.  La revisión de Cochrane definió los cánceres "por causa" de la siguiente manera:

</Para><OrderedList id="_124" Style="Arabic">
     <ListItem>Presunción clínica a partir de síntomas, examen digital del recto (EDR) anormal, o APE y confirmado por biopsia.
</ListItem><ListItem>El protocolo del estudio recomendó biopsia, pero no se realizó, y al final del estudio la biopsia mostró cáncer de próstata.
</ListItem><ListItem>La biopsia al final del estudio con APE menor de 4 ng/ml o EDR sospechoso que mostró cáncer de próstata.<Reference refidx="10"/></ListItem></OrderedList></SummarySection><SummarySection id="_125"><Title>Prevención por alimentación con frutas, vegetales y régimen alimentario bajo en grasa     
</Title><Para id="_126">Los resultados  de los estudios sobre la relación entre la ingesta alimentaria  de frutas y vegetales  y el riesgo de cáncer de próstata no son congruentes. En un estudio, se evaluaron  1.619 casos de cáncer de próstata y 1.618 controles  en una población  multicéntrica  y multiétnica.  EI estudio encontró que la ingesta de legumbres  y vegetales  crucíferos  y amarillos anaranjados estaba vinculada con    un riesgo menor de cáncer de  próstata.<Reference refidx="11"/></Para><Para id="_127">La European  Prospective  Investigation  into Cancer and Nutrition examinó la relación entre la ingesta de frutas y vegetales  y el cáncer de  próstata
subsiguiente. Tras un promedio  de seguimiento  de hasta 4,8 años,          1.104 de los 130.544 de los hombres participantes presentaron  cáncer de próstata.  No se observó  una relación estadísticamente  significativa  entre
la ingesta de frutas, vegetales  y vegetales  crucíferos y la de  ingesta de frutas y vegetales  combinados.<Reference refidx="12"/></Para><Para id="_128">En un estudio de intervención  alimentaria  durante  un período de 4 años, con reducción  de grasas y aumento  del consumo  de frutas, vegetales  y fibra, no tuvo efecto en las concentraciones   séricas de APE.<Reference refidx="13"/> Se desconoce  si la modificación  del régimen alimentario bajo en grasa, compuesto principalmente por alimentos  de origen vegetal, reduciría  el riesgo de cáncer de próstata.  Si bien se desconoce  este resultado,  se pueden vislumbrar  los múltiples beneficios  adicionales de este tipo de alimentación, que incluyen un riesgo reducido de hiperlipidemia,  un mejor control de la presión arterial, un riesgo menor de enfermedad  cardiovascular, los cuales ameritan la adopción  de este tipo de régimen alimentario.</Para></SummarySection><SummarySection id="_129"><Title>Quimioprevención</Title><Para id="_130">Si bien varias sustancias,  como tocoferol  α, selenio,  licopeno, difluorometilornitina,<Reference refidx="14"/><Reference refidx="15"/><Reference refidx="16"/><Reference refidx="17"/><Reference refidx="18"/> vitamina D,<Reference refidx="19"/><Reference refidx="20"/><Reference refidx="21"/> e isoflavonoides,<Reference refidx="22"/><Reference refidx="23"/> han mostrado  su potencial, ya sea en estudios clínicos o  de laboratorio,  para la quimioprevención  del cáncer de próstata, la correlación  de la prevención  del cáncer con estas sustancias  son una
preocupación  creciente,  dado el aumento  estadístico del riesgo de 
cáncer de próstata  observado  con el tocoferol  α en el ensayo SELECT y su carencia de efectos preventivos  (de hecho, un aumento  insignificante  del riesgo de cáncer de próstata)  con el uso de selenio.
</Para><SummarySection id="_131"><Title>Quimioprevención con selenio y vitamina  E</Title><Para id="_132">El Selenium  and Vitamin  E Cancer Prevention  Trial (SELECT
[NCT00006392])  fue un ensayo  numeroso, aleatorizado,  controlado  con placebo de vitamina  E y selenio,  en el que no se mostró reducción durante el período de incidencia del cáncer de próstata,  más bien, un aumento del riesgo de este cáncer con el uso de  la vitamina  E sola.<Reference refidx="24"/></Para><Para id="_133">En comparación  con el grupo de placebo, en el que 529 hombres presentaron  cáncer de próstata,  hubo un aumento estadísticamente significativo  de cáncer de próstata en el grupo de vitamina  E (620 casos), pero no el grupo de selenio  más vitamina  E (555 casos), o en el grupo de selenio (575 casos). La magnitud del aumento del riesgo del cáncer de próstata con la vitamina  E sola  fue de 17%. Resulta interesante notar que el aumento  estadístico  del riesgo de cáncer de próstata entre los hombres que recibieron vitamina  E se observe  tras la suspensión del complemento  en estudio, lo que indica el efecto prolongado de esta
sustancia.<Reference refidx="24"/></Para></SummarySection><SummarySection id="_134"><Title>Quimioprevención con licopeno</Title><Para id="_135">Hay datos probatorios de que una alimentación con contenido alto de frutas y vegetales se relaciona con un menor riesgo de cáncer.  Se desconoce  cuál micronutriente, si lo  hay,  es el responsable  de esta reducción.  Un grupo de nutrientes  que con frecuencia  se postula como portador de propiedades  quimiopreventivas   son los carotenoides.  El licopeno es el principal carotenoide  que consumen los estadounidenses  y presenta un número de posibles acciones,  como por ejemplo  su efecto antioxidante.<Reference refidx="25"/> Este se encuentra  en varios vegetales,  más notablemente  en el tomate, y su mejor forma de absorción es si se consume cocinado y acompañado de grasas y aceites alimenticios.</Para><Para id="_136">Los estudios  iniciales sobre la relación del licopeno y el riesgo de cáncer de próstata  fueron,  por lo general,  negativos antes de 1995, cuando solo se llevó a cabo un estudio de casos y controles  con 180 pacientes  que mostró una reducción  del riesgo.<Reference refidx="26"/><Reference refidx="27"/><Reference refidx="28"/><Reference refidx="29"/> En 1995, en un análisis del Physicians' Health Study, se encontró  una reducción de un tercio en el riesgo de cáncer de próstata en el grupo de hombres con el mayor consumo  de productos  provenientes del tomate, cuando se comparó con el grupo con el consumo más bajo, lo que se atribuyó  al contenido  de licopeno  de estos vegetales.<Reference refidx="30"/> Este análisis  numeroso  dio lugar a varios estudios posteriores, cuyos resultados  fueron  mixtos.<Reference refidx="31"/><Reference refidx="32"/> En una revisión de los datos publicados, se   concluyó  que las pruebas eran débiles en el sentido de que el licopeno estaba vinculado  con un riesgo reducido, ya que estudios
previos carecieron  de un control para la ingesta total de vegetales  (es decir, separar el efecto del tomate de los demás vegetales),  las evaluaciones sobre la ingesta alimentaria  están precariamente  diseñadas  para cuantificar  el consumo de licopeno y otros sesgos posibles.<Reference refidx="33"/> Está  por demostrarse que
una complementación  alimentaria  específica  con licopeno reduzca el riesgo de cáncer de próstata.  En el mayor estudio prospectivo  hasta la fecha, el Prostate Cancer  Prevention  Trial, el licopeno  no se relacionó                   con la reducción del riesgo de

cáncer de próstata en    9.559 hombres  participantes  en el estudio. De manera similar, no se encontró relación entre las concentraciones séricas de licopeno y el riesgo de cáncer de próstata. <Reference refidx="34"/><Reference refidx="35"/>
</Para></SummarySection></SummarySection><ReferenceSection><Citation idx="1" PMID="12824459" MedlineID="22750137">Thompson IM, Goodman PJ, Tangen CM, et al.: The influence of finasteride on the development of prostate cancer. N Engl J Med 349 (3): 215-24, 2003.</Citation><Citation idx="2" PMID="14644115">Thompson IM, Klein EA, Lippman SM, et al.: Prevention of prostate cancer with finasteride: US/European perspective. Eur Urol 44 (6): 650-5, 2003.</Citation><Citation idx="3" PMID="16280736">Andriole G, Bostwick D, Civantos F, et al.: The effects of 5alpha-reductase inhibitors on the natural history, detection and grading of prostate cancer: current state of knowledge. J Urol 174 (6): 2098-104, 2005.</Citation><Citation idx="4" PMID="16093979">Etzioni RD, Howlader N, Shaw PA, et al.: Long-term effects of finasteride on prostate specific antigen levels: results from the prostate cancer prevention trial. J Urol 174 (3): 877-81, 2005.</Citation><Citation idx="5" PMID="19328538">Kaplan SA, Roehrborn CG, Meehan AG, et al.: PCPT: Evidence that finasteride reduces risk of most frequently detected intermediate- and high-grade (Gleason score 6 and 7) cancer. Urology 73 (5): 935-9, 2009.</Citation><Citation idx="6" PMID="19138953">Redman MW, Tangen CM, Goodman PJ, et al.: Finasteride does not increase the risk of high-grade prostate cancer: a bias-adjusted modeling approach. Cancer Prev Res (Phila Pa) 1 (3): 174-81, 2008.</Citation><Citation idx="7" PMID="20357281">Andriole GL, Bostwick DG, Brawley OW, et al.: Effect of dutasteride on the risk of prostate cancer. N Engl J Med 362 (13): 1192-202, 2010.</Citation><Citation idx="8" PMID="7672814" MedlineID="95402973">Thompson I, Feigl P, Coltman C: Chemoprevention of prostate cancer with finasteride. Important Adv Oncol : 57-76, 1995.</Citation><Citation idx="9" PMID="8875211" MedlineID="97029199">Nelson PS, Gleason TP, Brawer MK: Chemoprevention for prostatic intraepithelial neoplasia. Eur Urol 30 (2): 269-78, 1996.</Citation><Citation idx="10" PMID="20977593">Wilt TJ, Macdonald R, Hagerty K, et al.: 5-α-Reductase inhibitors for prostate cancer chemoprevention: an updated Cochrane systematic review. BJU Int 106 (10): 1444-51, 2010.</Citation><Citation idx="11" PMID="10952096" MedlineID="20406628">Kolonel LN, Hankin JH, Whittemore AS, et al.: Vegetables, fruits, legumes and prostate cancer: a multiethnic case-control study. Cancer Epidemiol Biomarkers Prev 9 (8): 795-804, 2000.</Citation><Citation idx="12" PMID="14735477">Key TJ, Allen N, Appleby P, et al.: Fruits and vegetables and prostate cancer: no association among 1104 cases in a prospective study of 130544 men in the European Prospective Investigation into Cancer and Nutrition (EPIC). Int J Cancer 109 (1): 119-24, 2004 Mar10.</Citation><Citation idx="13" PMID="12202659" MedlineID="22191550">Shike M, Latkany L, Riedel E, et al.: Lack of effect of a low-fat, high-fruit, -vegetable, and -fiber diet on serum prostate-specific antigen of men without prostate cancer: results from a randomized trial. J Clin Oncol 20 (17): 3592-8, 2002.</Citation><Citation idx="14" PMID="6173280" MedlineID="82117885">Heby O: Role of polyamines in the control of cell proliferation and differentiation. Differentiation 19 (1): 1-20, 1981.</Citation><Citation idx="15" PMID="431333" MedlineID="79156030">Danzin C, Jung MJ, Grove J, et al.: Effect of alpha-difluoromethylornithine, an enzyme-activated irreversible inhibitor of ornithine decarboxylase, on polyamine levels in rat tissues. Life Sci 24 (6): 519-24, 1979.</Citation><Citation idx="16">Metcalf BW, Bey P, Danzin C, et al.: Catalytic irreversible inhibition of mammalian ornithine decarboxylase (E.C. 4.1.1.17) by substrate and product analogues. J Am Chem Soc  100(8): 2551-2553, 1978.</Citation><Citation idx="17" PMID="6812032" MedlineID="83014639">Heston WD, Kadmon D, Lazan DW, et al.: Copenhagen rat prostatic tumor ornithine decarboxylase activity (ODC) and the effect of the ODC inhibitor alpha-difluoromethylornithine. Prostate 3 (4): 383-9, 1982.</Citation><Citation idx="18" PMID="6422008" MedlineID="84137868">Abeloff MD, Slavik M, Luk GD, et al.: Phase I trial and pharmacokinetic studies of alpha-difluoromethylornithine--an inhibitor of polyamine biosynthesis. J Clin Oncol 2 (2): 124-30, 1984.</Citation><Citation idx="19" PMID="2241107" MedlineID="91053053">Schwartz GG, Hulka BS: Is vitamin D deficiency a risk factor for prostate cancer? (Hypothesis). Anticancer Res 10 (5A): 1307-11, 1990 Sep-Oct.</Citation><Citation idx="20" PMID="3024816" MedlineID="87077957">Eisman JA, Barkla DH, Tutton PJ: Suppression of in vivo growth of human cancer solid tumor xenografts by 1,25-dihydroxyvitamin D3. Cancer Res 47 (1): 21-5, 1987.</Citation><Citation idx="21" PMID="3840412" MedlineID="86027839">Chida K, Hashiba H, Fukushima M, et al.: Inhibition of tumor promotion in mouse skin by 1 alpha,25-dihydroxyvitamin D3. Cancer Res 45 (11 Pt 1): 5426-30, 1985.</Citation><Citation idx="22" PMID="7901532" MedlineID="94048652">Adlercreutz H, Markkanen H, Watanabe S: Plasma concentrations of phyto-oestrogens in Japanese men. Lancet 342 (8881): 1209-10, 1993.</Citation><Citation idx="23" PMID="8497428" MedlineID="93268675">Peterson G, Barnes S: Genistein and biochanin A inhibit the growth of human prostate cancer cells but not epidermal growth factor receptor tyrosine autophosphorylation. Prostate 22 (4): 335-45, 1993.</Citation><Citation idx="24" PMID="21990298">Klein EA, Thompson IM Jr, Tangen CM, et al.: Vitamin E and the risk of prostate cancer: the Selenium and Vitamin E Cancer Prevention Trial (SELECT). JAMA 306 (14): 1549-56, 2011.</Citation><Citation idx="25" PMID="9100211" MedlineID="97254801">Gerster H: The potential role of lycopene for human health. J Am Coll Nutr 16 (2): 109-26, 1997.</Citation><Citation idx="26" PMID="2342127" MedlineID="90258065">Hsing AW, Comstock GW, Abbey H, et al.: Serologic precursors of cancer. Retinol, carotenoids, and tocopherol and risk of prostate cancer. J Natl Cancer Inst 82 (11): 941-6, 1990.</Citation><Citation idx="27" PMID="2743254" MedlineID="89303712">Mills PK, Beeson WL, Phillips RL, et al.: Cohort study of diet, lifestyle, and prostate cancer in Adventist men. Cancer 64 (3): 598-604, 1989.</Citation><Citation idx="28">Schuman LM, Mandel JS, Radke A, et al.: Some selected features of the epidemiology of prostatic cancer: Minneapolis-St. Paul, Minnesota case-control study, 1976-1979. [Abstract] Trends in Cancer Incidence: Causes and Practical Implications (Proceedings of a Symposium Held in Oslo, Norway, Aug. 6-7, 1980)  pp 345-354.</Citation><Citation idx="29" PMID="2000838" MedlineID="91157853">Le Marchand L, Hankin JH, Kolonel LN, et al.: Vegetable and fruit consumption in relation to prostate cancer risk in Hawaii: a reevaluation of the effect of dietary beta-carotene. Am J Epidemiol 133 (3): 215-9, 1991.</Citation><Citation idx="30" PMID="7473833" MedlineID="96077078">Giovannucci E, Ascherio A, Rimm EB, et al.: Intake of carotenoids and retinol in relation to risk of prostate cancer. J Natl Cancer Inst 87 (23): 1767-76, 1995.</Citation><Citation idx="31" PMID="10578485" MedlineID="20045447">Jain MG, Hislop GT, Howe GR, et al.: Plant foods, antioxidants, and prostate cancer risk: findings from case-control studies in Canada. Nutr Cancer 34 (2): 173-84, 1999.</Citation><Citation idx="32" PMID="9303371" MedlineID="97447631">Key TJ, Silcocks PB, Davey GK, et al.: A case-control study of diet and prostate cancer. Br J Cancer 76 (5): 678-87, 1997.</Citation><Citation idx="33" PMID="10645814" MedlineID="20108412">Kristal AR, Cohen JH: Invited commentary: tomatoes, lycopene, and prostate cancer. How strong is the evidence? Am J Epidemiol 151 (2): 124-7; discussion 128-30, 2000.</Citation><Citation idx="34" PMID="21335507">Kristal AR, Till C, Platz EA, et al.: Serum lycopene concentration and prostate cancer risk: results from the Prostate Cancer Prevention Trial. Cancer Epidemiol Biomarkers Prev 20 (4): 638-46, 2011.</Citation><Citation idx="35" PMID="20693267">Kristal AR, Arnold KB, Neuhouser ML, et al.: Diet, supplement use, and prostate cancer risk: results from the prostate cancer prevention trial. Am J Epidemiol 172 (5): 566-77, 2010.</Citation></ReferenceSection></SummarySection><SummarySection id="_83"><SectMetaData><SectionType>Changes to summary</SectionType></SectMetaData><Title>Modificaciones a este sumario (02/13/2015)</Title><Para id="_84">Los sumarios del PDQ con información sobre el cáncer se revisan con regularidad y se actualizan en la medida en que se obtiene nueva información.  Esta sección describe los cambios más recientes introducidos en este sumario a partir de la fecha arriba indicada.</Para><Para id="_138"><Strong><SummaryRef href="CDR0000747947#_25" url="/espanol/tipos/prostata/pro/prevencion-prostata-pdq">Significación</SummaryRef></Strong></Para><Para id="_139">Se actualizaron las <SummaryRef href="CDR0000747947#_27" url="/espanol/tipos/prostata/pro/prevencion-prostata-pdq">estadísticas</SummaryRef> con el cálculo de casos nuevos y defunciones en 2015 (se citó a la American Cancer Society como referencia 1).</Para><Para id="_disclaimerHP_3">Este sumario está redactado y mantenido por el <ExternalRef xref="http://www.cancer.gov/espanol/pdq/deteccion-prevencion-consejoeditorial">Consejo Editorial del PDQ® de Exámenes de Detección y Prevención</ExternalRef>, que es editorialmente independiente del NCI. El sumario refleja una revisión independiente de la bibliografía y no representa una declaración de políticas del NCI o de los NIH. Para mayor información sobre las políticas de los sumarios y la función de los  consejos editoriales  del PDQ que mantienen los sumarios del PDQ, consultar en <SummaryRef href="CDR0000747947#_AboutThis_1" url="http://www.cancer.gov/espanol/tipos/prostata/pro/prevencion-prostata-pdq">Información sobre este sumario del PDQ</SummaryRef> y  la página sobre <ExternalRef xref="http://www.cancer.gov/espanol/recursos/pdq">Banco de datos de información de cáncer (PDQ®)</ExternalRef>.
</Para></SummarySection> 
  <SummarySection id="_ContactUs_2"><Title>Preguntas u opiniones sobre este sumario</Title><Para id="_ContactUs_3">Si tiene preguntas o algún  comentario sobre este sumario, por favor envíelas a través  del <ExternalRef xref="http://www.cancer.gov/espanol/instituto/correo-electronico">formulario de opinión</ExternalRef> disponible  en nuestro portal de Internet, Cancer.gov/espanol.</Para></SummarySection> 
  <SummarySection id="_AboutThis_1"><Title>Información sobre este sumario del PDQ</Title><SummarySection id="_AboutThis_2"><Title>Propósito de este sumario</Title><Para id="_AboutThis_3">Este sumario del PDQ con información sobre el cáncer para profesionales de la salud provee información integral, revisada por expertos, con base en los datos probatorios sobre prevención del cáncer de próstata. Su propósito es servir como fuente de información y ayuda para los médicos que atienden a pacientes de cáncer. No  provee pautas o recomendaciones formales para la toma de decisiones relacionadas con la atención de la salud.</Para></SummarySection><SummarySection id="_AboutThis_21"><Title>Revisores y actualizaciones</Title><Para id="_AboutThis_22">El  <ExternalRef xref="http://www.cancer.gov/espanol/pdq/deteccion-prevencion-consejoeditorial">Consejo Editorial del PDQ® de Exámenes de Detección y Prevención</ExternalRef> revisa y actualiza regularmente este sumario a medida que es necesario,   el cual es editorialmente independiente del Instituto Nacional del Cáncer. El sumario refleja un revisión independiente de la literatura médica y no representa la política del Instituto Nacional del Cáncer  o los Institutos Nacionales de la Salud.</Para><Para id="_AboutThis_26">Los miembros de este Consejo revisan mensualmente los artículos recién publicados para determinar si un artículo debería:</Para><ItemizedList id="_AboutThis_23" Style="bullet"><ListItem>discutirse en una reunión,</ListItem><ListItem>citarse incluyendo el texto, o</ListItem><ListItem>sustituir o actualizar un artículo ya citado.</ListItem></ItemizedList><Para id="_AboutThis_24">Los cambios en los sumarios se deciden por medio de un proceso de consenso durante el que los miembros del Consejo evalúan la solidez de los datos probatorios en los artículos publicados y determinan la forma en que se debe incluir el artículo en el sumario.</Para><Para id="_AboutThis_25">Cualquier comentario o pregunta sobre el contenido de este sumario se debe enviar a la página del Internet Cancer.gov/espanol del NCI utilizando el   <ExternalRef xref="http://www.cancer.gov/espanol/instituto/correo-electronico">Formulario de comunicación</ExternalRef> (<Emphasis>Contact Form</Emphasis>).  Se solicita no comunicarse con los miembros del Consejo para presentar preguntas o comentarios sobre los sumarios.  Los miembros del Consejo no responderán preguntas individuales. </Para></SummarySection><SummarySection id="_AboutThis_9"><Title>Grados de comprobación científica</Title><Para id="_AboutThis_10">Algunas referencias bibliográficas en este sumario vienen seguidas de un grado de comprobación científica. Estas designaciones tienen el propósito de ayudar al lector a evaluar la solidez de los hechos científico-estadísticos que sustentan el uso de  intervenciones  o abordajes específicos. El Consejo Editorial del PDQ® de Exámenes de Detección y Prevención utiliza un <SummaryRef href="CDR0000733829" url="/espanol/publicaciones/pdq/grados-comprobacion/deteccion-prevencion">sistema formal de jerarquización de la medicina factual</SummaryRef> para establecer  las designaciones del grado de comprobación científica.</Para></SummarySection><SummarySection id="_AboutThis_11"><Title>Permisos para el uso de este sumario</Title><Para id="_AboutThis_12">PDQ es una marca registrada. Aunque el contenido de los documentos del PDQ se puede usar libremente como texto, este no se puede identificar como un sumario de información sobre cáncer del PDQ del  NCI  a menos que se reproduzca en su totalidad y se actualice regularmente. Sin embargo, se permitirá que un autor  escriba una oración como, por ejemplo, “El sumario con información sobre el cáncer del PDQ del NCI sobre prevención del cáncer de mama indica los siguientes riesgos de manera suscinta: [incluir fragmento del sumario]”.</Para><Para id="_AboutThis_13">El formato preferido para una referencia bibliográfica de este sumario del PDQ es el siguiente:</Para><Para id="_AboutThis_14">National Cancer Institute: PDQ® Prevención del cáncer de próstata. Bethesda, MD: National Cancer Institute. Última actualización:  &lt;MM/DD/YYYY&gt;. Disponible en: <ExternalRef xref="http://www.cancer.gov/espanol/tipos/prostata/pro/prevencion-prostata-pdq">http://www.cancer.gov/espanol/tipos/prostata/pro/prevencion-prostata-pdq</ExternalRef>.  Fecha de acceso: &lt;MM/DD/YYYY&gt;.</Para><Para id="_AboutThis_15">Las imágenes incluidas en este sumario se usan con permiso del autor, el artista o la casa editorial para su sola inclusión en los sumarios del PDQ. El permiso para usar las imágenes fuera del contexto de información del PDQ se debe obtener del propietario; el Instituto Nacional del Cáncer no lo puede otorgar. Para mayor información sobre el uso de las gráficas de este sumario, así como de muchas otras imágenes relacionadas con el cáncer, consultar <ExternalRef xref="http://visualsonline.cancer.gov/">Visual Online</ExternalRef>, una colección de más de 2.000 imágenes científicas.</Para></SummarySection><SummarySection id="_AboutThis_16"><Title>Cláusula sobre el descargo de responsabilidad</Title><Para id="_AboutThis_18">La información en estos sumarios  no se debe utilizar como base para determinar reembolsos por cuenta de las aseguradoras. Para mayor información  sobre cobertura de seguros, consultar la página <ExternalRef xref="http://www.cancer.gov/espanol/cancer/sobrellevar/financiera-legal">Cómo hacer frente al cáncer</ExternalRef> disponible en Cancer.gov.</Para></SummarySection><SummarySection id="_AboutThis_19"><Title>Para mayor información</Title><Para id="_AboutThis_20">En Cancer.gov/espanol,  se ofrece más información sobre cómo comunicarse o recibir ayuda en la página <ExternalRef xref="http://www.cancer.gov/espanol/contactenos">¿En qué podemos ayudarle?</ExternalRef>.   
Las preguntas también se pueden enviar por correo electrónico  utilizando el <ExternalRef xref="http://www.cancer.gov/espanol/instituto/correo-electronico">Formulario de comunicación</ExternalRef>.</Para></SummarySection></SummarySection> 
   
  <SummarySection id="_GetMore_28"><Title>Obtenga más información del NCI</Title><Para id="_GetMore_30"><Emphasis><Strong>Llame al 1-800-4-CANCER</Strong></Emphasis></Para><Para id="_GetMore_31">Para obtener más información, las personas que residen en los Estados Unidos  pueden llamar gratis al Servicio de Información del Instituto Nacional del Cáncer (NCI) al 1-800-4-CANCER (1-800-422-6237), de lunes a viernes de 8:00 a. m. a 8:00 p. m, hora del Este.    Un especialista en información sobre el cáncer estará disponible para responder a sus preguntas.</Para><Para id="_GetMore_42"><Emphasis><Strong>Escríbanos</Strong></Emphasis></Para><Para id="_GetMore_43">Para obtener información del NCI, sírvase escribir a la siguiente dirección:</Para><ItemizedList id="_GetMore_44" Style="simple"><ListItem>NCI Public Inquiries Office</ListItem><ListItem>9609 Medical Center Dr. </ListItem><ListItem>Room 2E532 MSC 9760</ListItem><ListItem>Bethesda, MD  20892-9760</ListItem></ItemizedList><Para id="_GetMore_32"><Emphasis><Strong>Busque en el portal de  Internet del NCI</Strong></Emphasis></Para><Para id="_GetMore_33">

El <ExternalRef xref="http://www.cancer.gov/espanol">portal de Internet del NCI</ExternalRef> provee acceso en línea a  información sobre el cáncer, ensayos clínicos, y otros portales de Internet u organizaciones que ofrecen servicios de apoyo y recursos para los pacientes con cáncer y sus familias. Para una búsqueda rápida, use la casilla de búsqueda en la esquina superior derecha de cada página Web.  Los resultados de una gama amplia de términos buscados incluirán una lista de las “Mejores Opciones,”  páginas web que son escogidas de forma editorial que se asemejan bastante al término que usted busca.</Para><Para id="_GetMore_45">Hay muchos  lugares donde las personas pueden obtener materiales e información sobre tratamientos para el cáncer y servicios.  Los hospitales  pueden tener información sobre instituciones o regionales que ofrecen información sobre ayuda financiera, transporte de ida y vuelta para recibir tratamiento, atención en el hogar y sobre cómo abordar otros problemas relacionados con el tratamiento del cáncer.</Para><Para id="_GetMore_34"><Emphasis><Strong>Publicaciones</Strong></Emphasis></Para><Para id="_GetMore_35">El NCI tiene folletos y otros materiales para pacientes, profesionales de la salud y el público en general.  Estas publicaciones describen los diferentes tipos de cáncer, los métodos para tratarlo, pautas para hacerle frente  e información sobre ensayos clínicos.  Algunas publicaciones proveen información sobre las diferentes pruebas de detección del cáncer, sus causas y cómo prevenirlo, además de estadísticas e información sobre actividades de investigación llevadas a cabo en el NCI. Los materiales del NCI sobre estos y otros temas, se pueden solicitar en línea al <ExternalRef xref="https://pubs.cancer.gov/ncipl">Servicio de Localización de Publicaciones del Instituto Nacional del Cáncer</ExternalRef> (National Cancer Institute Publications Locator) o imprimirse directamente. Estos materiales también se pueden solicitar con una llamada gratuita al Servicio de Información sobre el Cáncer del Instituto Nacional del Cáncer (National Cancer Institute's Cancer Information Service) al 1-800-4-CANCER (1-800-422-6237).</Para></SummarySection><TranslationOf ref="CDR0000062833"/><DateFirstPublished>2013-06-21</DateFirstPublished><DateLastModified>2015-02-13</DateLastModified></Summary>
